pyIGRF14/__init__.py
pyIGRF14/calculate.py
pyIGRF14/loadCoeffs.py
pyIGRF14/value.py
pyIGRF14/src/igrf13coeffs.txt
pyIGRF14/src/igrf14coeffs.txt
pyigrf14-1.0.4.dist-info/licenses/LICENSE
pyigrf14-1.0.4.dist-info/WHEEL
pyigrf14-1.0.4.dist-info/METADATA
pyigrf14-1.0.4.dist-info/RECORD
