Metadata-Version: 2.4
Name: pyIGRF14
Version: 1.0.4
Summary: This is a package of IGRF-14 (International Geomagnetic Reference Field) about python version.
Author-email: zzyztyy <2375672032@qq.com>
Maintainer-email: Jonathan Dekhtiar <jonathan@dekhtiar.com>
Requires-Python: >=3.10
License-File: LICENSE
Requires-Dist: numpy
Requires-Dist: pytest ; extra == "test"
Requires-Dist: goto-statement>=1.2,<2.0 ; extra == "test"
Project-URL: Homepage, https://pypi.org/project/pyIGRF14/
Project-URL: Repository, https://github.com/OpenSpeleo/pyIGRF14
Provides-Extra: test
